task_adaptation/__init__.py
task_adaptation/adapt_and_eval.py
task_adaptation/data_loader.py
task_adaptation/data_loader_test.py
task_adaptation/loop.py
task_adaptation/loop_test.py
task_adaptation/model.py
task_adaptation/model_test.py
task_adaptation/registry.py
task_adaptation/registry_test.py
task_adaptation/test_utils.py
task_adaptation/trainer.py
task_adaptation/trainer_test.py
task_adaptation/data/__init__.py
task_adaptation/data/base.py
task_adaptation/data/base_test.py
task_adaptation/data/caltech.py
task_adaptation/data/caltech_test.py
task_adaptation/data/cars.py
task_adaptation/data/cars_test.py
task_adaptation/data/cifar.py
task_adaptation/data/cifar_test.py
task_adaptation/data/clevr.py
task_adaptation/data/clevr_test.py
task_adaptation/data/cub.py
task_adaptation/data/cub_test.py
task_adaptation/data/data_testing_lib.py
task_adaptation/data/diabetic_retinopathy.py
task_adaptation/data/diabetic_retinopathy_test.py
task_adaptation/data/dmlab.py
task_adaptation/data/dmlab_test.py
task_adaptation/data/dsprites.py
task_adaptation/data/dsprites_test.py
task_adaptation/data/dtd.py
task_adaptation/data/dtd_test.py
task_adaptation/data/eurosat.py
task_adaptation/data/eurosat_test.py
task_adaptation/data/food101.py
task_adaptation/data/food101_test.py
task_adaptation/data/inaturalist.py
task_adaptation/data/inaturalist_test.py
task_adaptation/data/kitti.py
task_adaptation/data/kitti_test.py
task_adaptation/data/oxford_flowers102.py
task_adaptation/data/oxford_flowers102_test.py
task_adaptation/data/oxford_iiit_pet.py
task_adaptation/data/oxford_iiit_pet_test.py
task_adaptation/data/patch_camelyon.py
task_adaptation/data/patch_camelyon_test.py
task_adaptation/data/resisc45.py
task_adaptation/data/resisc45_test.py
task_adaptation/data/smallnorb.py
task_adaptation/data/smallnorb_test.py
task_adaptation/data/sun397.py
task_adaptation/data/sun397_test.py
task_adaptation/data/svhn.py
task_adaptation/data/svhn_test.py
task_adaptation-0.1.dist-info/AUTHORS
task_adaptation-0.1.dist-info/LICENSE
task_adaptation-0.1.dist-info/METADATA
task_adaptation-0.1.dist-info/WHEEL
task_adaptation-0.1.dist-info/top_level.txt
task_adaptation-0.1.dist-info/RECORD
